{
    "version": "0.10.0",
    "description": "Minimal Static Page Generator",
    "homepage": "https://github.com/hymkor/minipage",
    "license": "MIT License",
    "architecture": {
        "64bit": {
            "url": "https://github.com/hymkor/minipage/releases/download/v0.10.0/minipage-v0.10.0-windows-amd64.zip",
            "hash": "2eb6b17fe04bdd93fb72d49e745ec3559f7cb5ae016b82c6f8df5cff3d2bcbae"
        }
    },
    "bin": "minipage.exe",
    "checkver": "github",
    "autoupdate": {
        "architecture": {
            "64bit": {
                "url": "https://github.com/hymkor/minipage/releases/download/v$version/minipage-v$version-windows-amd64.zip"
            }
        }
    }
}
