{
    "version": "9.1.0105",
    "description": "Vim Win32 Installer",
    "homepage": "https://github.com/vim/vim-win32-installer",
    "license": "Vim",
    "architecture": {
        "32bit": {
            "url": "https://github.com/vim/vim-win32-installer/releases/download/v9.1.0105/gvim_9.1.0105_x86.zip",
            "hash": "c8f836971fb56d22975dcc6b6edfc18ff8a596c03e524bde23324f638a0bf960"
        },
        "64bit": {
            "url": "https://github.com/vim/vim-win32-installer/releases/download/v9.1.0105/gvim_9.1.0105_x64.zip",
            "hash": "25c9326a61dcbcbf03931b88cec60d93bcdec30d1c5be73e3eaedb8cc6737a11"
        }
    },
    "bin": [
        "vim/vim91/diff.exe",
        "vim/vim91/gvim.exe",
        "vim/vim91/install.exe",
        "vim/vim91/tee.exe",
        "vim/vim91/uninstall.exe",
        "vim/vim91/vim.exe",
        "vim/vim91/vimrun.exe",
        "vim/vim91/winpty-agent.exe",
        "vim/vim91/xxd.exe"
    ],
    "checkver": "github",
    "autoupdate": {
        "architecture": {
            "32bit": {
                "url": "https://github.com/vim/vim-win32-installer/releases/download/v$version/gvim_$version_x86.zip"
            },
            "64bit": {
                "url": "https://github.com/vim/vim-win32-installer/releases/download/v$version/gvim_$version_x64.zip"
            }
        }
    }
}
